[
    {
        "brand": "Citroen",
        "model": "2024 Citroen Berlingo",
        "price": "119.8 - 138.9",
        "url": "https://autos.yahoo.com.tw/new-cars/model/citroen-berlingo-2024"
    },
    {
        "brand": "Citroen",
        "model": "2024 Citroen C4",
        "price": "106.9 - 119.9",
        "url": "https://autos.yahoo.com.tw/new-cars/model/citroen-c4-2024"
    },
    {
        "brand": "Citroen",
        "model": "2024 Citroen C5 Aircross",
        "price": "139.9 - 155.9",
        "url": "https://autos.yahoo.com.tw/new-cars/model/citroen-c5-aircross-2024"
    },
    {
        "brand": "Citroen",
        "model": "2023 Citroen Berlingo",
        "price": "118.8 - 138.9",
        "url": "https://autos.yahoo.com.tw/new-cars/model/citroen-berlingo-2023"
    },
    {
        "brand": "Citroen",
        "model": "2023 Citroen C4",
        "price": "106.9 - 119.9",
        "url": "https://autos.yahoo.com.tw/new-cars/model/citroen-c4-2023"
    },
    {
        "brand": "Citroen",
        "model": "2023 Citroen C5 Aircross",
        "price": "139.9 - 155.9",
        "url": "https://autos.yahoo.com.tw/new-cars/model/citroen-c5-aircross-2023"
    },
    {
        "brand": "Citroen",
        "model": "2023 Citroen E-C4",
        "price": "153.9 - 153.9",
        "url": "https://autos.yahoo.com.tw/new-cars/model/citroen-e-c4-2023"
    },
    {
        "brand": "Citroen",
        "model": "2022 Citroen Berlingo",
        "price": "118.8 - 138.8",
        "url": "https://autos.yahoo.com.tw/new-cars/model/citroen-berlingo-2022"
    },
    {
        "brand": "Citroen",
        "model": "2022 Citroen C5 Aircross",
        "price": "130.9 - 155.9",
        "url": "https://autos.yahoo.com.tw/new-cars/model/citroen-c5-aircross-2022"
    },
    {
        "brand": "Citroen",
        "model": "2021 Citroen Berlingo",
        "price": "114.8 - 134.8",
        "url": "https://autos.yahoo.com.tw/new-cars/model/citroen-berlingo-2021"
    },
    {
        "brand": "Citroen",
        "model": "2021 Citroen C5 Aircross",
        "price": "130.9 - 151.9",
        "url": "https://autos.yahoo.com.tw/new-cars/model/citroen-c5-aircross-2021"
    },
    {
        "brand": "Citroen",
        "model": "2020 Citroen Berlingo",
        "price": "98.8 - 129.8",
        "url": "https://autos.yahoo.com.tw/new-cars/model/citroen-berlingo-2020"
    },
    {
        "brand": "Citroen",
        "model": "2020 Citroen C4 Picasso",
        "price": "155.8 - 158.8",
        "url": "https://autos.yahoo.com.tw/new-cars/model/citroen-c4-picasso-2020"
    },
    {
        "brand": "Citroen",
        "model": "2020 Citroen C5 Aircross",
        "price": "138.8 - 155.8",
        "url": "https://autos.yahoo.com.tw/new-cars/model/citroen-c5-aircross-2020"
    },
    {
        "brand": "Citroen",
        "model": "2020 Citroen Grand C4 SpaceTourer",
        "price": "159.8 - 178.8",
        "url": "https://autos.yahoo.com.tw/new-cars/model/citroen-grand-c4-spacetourer-2020"
    },
    {
        "brand": "Citroen",
        "model": "2019 Citroen Berlingo",
        "price": "98.8 - 129.8",
        "url": "https://autos.yahoo.com.tw/new-cars/model/citroen-berlingo-2019"
    },
    {
        "brand": "Citroen",
        "model": "2019 Citroen C4 Picasso",
        "price": "139.8 - 158.8",
        "url": "https://autos.yahoo.com.tw/new-cars/model/citroen-c4-picasso-2019"
    },
    {
        "brand": "Citroen",
        "model": "2019 Citroen C5 Aircross",
        "price": "138.8 - 155.8",
        "url": "https://autos.yahoo.com.tw/new-cars/model/citroen-c5-aircross-2019"
    },
    {
        "brand": "Citroen",
        "model": "2019 Citroen DS 5",
        "price": "169.8 - 169.8",
        "url": "https://autos.yahoo.com.tw/new-cars/model/citroen-ds-5-2019"
    },
    {
        "brand": "Citroen",
        "model": "2019 Citroen Grand C4 Picasso",
        "price": "158.8 - 173.8",
        "url": "https://autos.yahoo.com.tw/new-cars/model/citroen-grand-c4-picasso-2019"
    },
    {
        "brand": "Citroen",
        "model": "2019 Citroen Grand C4 SpaceTourer",
        "price": "159.8 - 178.8",
        "url": "https://autos.yahoo.com.tw/new-cars/model/citroen-grand-c4-spacetourer-2019"
    },
    {
        "brand": "Citroen",
        "model": "2018 Citroen C4 Picasso",
        "price": "139.8 - 158.8",
        "url": "https://autos.yahoo.com.tw/new-cars/model/citroen-c4-picasso-2018"
    },
    {
        "brand": "Citroen",
        "model": "2018 Citroen DS 5",
        "price": "169.8 - 189.8",
        "url": "https://autos.yahoo.com.tw/new-cars/model/citroen-ds-5-2018"
    },
    {
        "brand": "Citroen",
        "model": "2018 Citroen Grand C4 Picasso",
        "price": "158.8 - 173.8",
        "url": "https://autos.yahoo.com.tw/new-cars/model/citroen-grand-c4-picasso-2018"
    },
    {
        "brand": "Citroen",
        "model": "2017 Citroen C3 Picasso",
        "price": "86.8 - 96.8",
        "url": "https://autos.yahoo.com.tw/new-cars/model/citroen-c3-picasso-2017"
    },
    {
        "brand": "Citroen",
        "model": "2017 Citroen C4 Picasso",
        "price": "152.8 - 192.8",
        "url": "https://autos.yahoo.com.tw/new-cars/model/citroen-c4-picasso-2017"
    },
    {
        "brand": "Citroen",
        "model": "2017 Citroen DS 3",
        "price": "110 - 115.5",
        "url": "https://autos.yahoo.com.tw/new-cars/model/citroen-ds-3-2017"
    },
    {
        "brand": "Citroen",
        "model": "2017 Citroen DS 5",
        "price": "169.8 - 189.8",
        "url": "https://autos.yahoo.com.tw/new-cars/model/citroen-ds-5-2017"
    },
    {
        "brand": "Citroen",
        "model": "2017 Citroen Grand C4 Picasso",
        "price": "178.8 - 212.8",
        "url": "https://autos.yahoo.com.tw/new-cars/model/citroen-grand-c4-picasso-2017"
    },
    {
        "brand": "Citroen",
        "model": "2016 Citroen C3 Picasso",
        "price": "86.8 - 96.8",
        "url": "https://autos.yahoo.com.tw/new-cars/model/citroen-c3-picasso-2016"
    },
    {
        "brand": "Citroen",
        "model": "2016 Citroen C4 Picasso",
        "price": "162.8 - 192.8",
        "url": "https://autos.yahoo.com.tw/new-cars/model/citroen-c4-picasso-2016"
    },
    {
        "brand": "Citroen",
        "model": "2016 Citroen DS 3",
        "price": "99 - 105",
        "url": "https://autos.yahoo.com.tw/new-cars/model/citroen-ds-3-2016"
    },
    {
        "brand": "Citroen",
        "model": "2016 Citroen DS 5",
        "price": "169.8 - 189.8",
        "url": "https://autos.yahoo.com.tw/new-cars/model/citroen-ds-5-2016"
    },
    {
        "brand": "Citroen",
        "model": "2016 Citroen Grand C4 Picasso",
        "price": "178.8 - 212.8",
        "url": "https://autos.yahoo.com.tw/new-cars/model/citroen-grand-c4-picasso-2016"
    },
    {
        "brand": "Citroen",
        "model": "2015 Citroen C3 Picasso",
        "price": "86.8 - 96.8",
        "url": "https://autos.yahoo.com.tw/new-cars/model/citroen-c3-picasso-2015"
    },
    {
        "brand": "Citroen",
        "model": "2015 Citroen C4 Picasso",
        "price": "162.8 - 192.8",
        "url": "https://autos.yahoo.com.tw/new-cars/model/citroen-c4-picasso-2015"
    },
    {
        "brand": "Citroen",
        "model": "2015 Citroen DS 3",
        "price": "99 - 105",
        "url": "https://autos.yahoo.com.tw/new-cars/model/citroen-ds-3-2015"
    },
    {
        "brand": "Citroen",
        "model": "2015 Citroen DS 5",
        "price": "169.8 - 189.8",
        "url": "https://autos.yahoo.com.tw/new-cars/model/citroen-ds-5-2015"
    },
    {
        "brand": "Citroen",
        "model": "2015 Citroen Grand C4 Picasso",
        "price": "178.8 - 212.8",
        "url": "https://autos.yahoo.com.tw/new-cars/model/citroen-grand-c4-picasso-2015"
    }
]