[
    {
        "brand": "Jaguar",
        "model": "2024 Jaguar E-Pace",
        "price": "218 - 218",
        "url": "https://autos.yahoo.com.tw/new-cars/model/jaguar-e-pace-2024"
    },
    {
        "brand": "Jaguar",
        "model": "2024 Jaguar F-Pace",
        "price": "310 - 508",
        "url": "https://autos.yahoo.com.tw/new-cars/model/jaguar-f-pace-2024"
    },
    {
        "brand": "Jaguar",
        "model": "2024 Jaguar F-Type",
        "price": "575 - 575",
        "url": "https://autos.yahoo.com.tw/new-cars/model/jaguar-f-type-2024"
    },
    {
        "brand": "Jaguar",
        "model": "2024 Jaguar F-Type Coupe",
        "price": "381 - 715",
        "url": "https://autos.yahoo.com.tw/new-cars/model/jaguar-f-type-coupe-2024"
    },
    {
        "brand": "Jaguar",
        "model": "2024 Jaguar I-Pace",
        "price": "298 - 332",
        "url": "https://autos.yahoo.com.tw/new-cars/model/jaguar-i-pace-2024"
    },
    {
        "brand": "Jaguar",
        "model": "2023 Jaguar E-Pace",
        "price": "210 - 228",
        "url": "https://autos.yahoo.com.tw/new-cars/model/jaguar-e-pace-2023"
    },
    {
        "brand": "Jaguar",
        "model": "2023 Jaguar F-Pace",
        "price": "286 - 501",
        "url": "https://autos.yahoo.com.tw/new-cars/model/jaguar-f-pace-2023"
    },
    {
        "brand": "Jaguar",
        "model": "2023 Jaguar F-Type Coupe",
        "price": "377 - 500",
        "url": "https://autos.yahoo.com.tw/new-cars/model/jaguar-f-type-coupe-2023"
    },
    {
        "brand": "Jaguar",
        "model": "2023 Jaguar I-Pace",
        "price": "297 - 331",
        "url": "https://autos.yahoo.com.tw/new-cars/model/jaguar-i-pace-2023"
    },
    {
        "brand": "Jaguar",
        "model": "2022 Jaguar E-Pace",
        "price": "206 - 225",
        "url": "https://autos.yahoo.com.tw/new-cars/model/jaguar-e-pace-2022"
    },
    {
        "brand": "Jaguar",
        "model": "2022 Jaguar F-Pace",
        "price": "275 - 473",
        "url": "https://autos.yahoo.com.tw/new-cars/model/jaguar-f-pace-2022"
    },
    {
        "brand": "Jaguar",
        "model": "2022 Jaguar F-Type Coupe",
        "price": "367 - 487",
        "url": "https://autos.yahoo.com.tw/new-cars/model/jaguar-f-type-coupe-2022"
    },
    {
        "brand": "Jaguar",
        "model": "2022 Jaguar I-Pace",
        "price": "348 - 348",
        "url": "https://autos.yahoo.com.tw/new-cars/model/jaguar-i-pace-2022"
    },
    {
        "brand": "Jaguar",
        "model": "2022 Jaguar XE",
        "price": "219 - 219",
        "url": "https://autos.yahoo.com.tw/new-cars/model/jaguar-xe-2022"
    },
    {
        "brand": "Jaguar",
        "model": "2021 Jaguar F-Pace",
        "price": "278 - 299",
        "url": "https://autos.yahoo.com.tw/new-cars/model/jaguar-f-pace-2021"
    },
    {
        "brand": "Jaguar",
        "model": "2021 Jaguar F-Type Coupe",
        "price": "366 - 486",
        "url": "https://autos.yahoo.com.tw/new-cars/model/jaguar-f-type-2021"
    },
    {
        "brand": "Jaguar",
        "model": "2021 Jaguar I-Pace",
        "price": "346 - 346",
        "url": "https://autos.yahoo.com.tw/new-cars/model/jaguar-i-pace-2021"
    },
    {
        "brand": "Jaguar",
        "model": "2021 Jaguar XE",
        "price": "218 - 218",
        "url": "https://autos.yahoo.com.tw/new-cars/model/jaguar-xe-2021"
    },
    {
        "brand": "Jaguar",
        "model": "2021 Jaguar XF",
        "price": "310 - 310",
        "url": "https://autos.yahoo.com.tw/new-cars/model/jaguar-xf-2021"
    },
    {
        "brand": "Jaguar",
        "model": "2020 Jaguar E-Pace",
        "price": "188 - 224",
        "url": "https://autos.yahoo.com.tw/new-cars/model/jaguar-e-pace-2020"
    },
    {
        "brand": "Jaguar",
        "model": "2020 Jaguar F-Pace",
        "price": "300 - 462",
        "url": "https://autos.yahoo.com.tw/new-cars/model/jaguar-f-pace-2020"
    },
    {
        "brand": "Jaguar",
        "model": "2020 Jaguar F-Type Coupe",
        "price": "363 - 763",
        "url": "https://autos.yahoo.com.tw/new-cars/model/jaguar-f-type-coupe-2020"
    },
    {
        "brand": "Jaguar",
        "model": "2020 Jaguar I-Pace",
        "price": "333 - 377",
        "url": "https://autos.yahoo.com.tw/new-cars/model/jaguar-i-pace-2019"
    },
    {
        "brand": "Jaguar",
        "model": "2020 Jaguar XE",
        "price": "216 - 237",
        "url": "https://autos.yahoo.com.tw/new-cars/model/jaguar-xe-2020"
    },
    {
        "brand": "Jaguar",
        "model": "2020 Jaguar XF",
        "price": "289 - 289",
        "url": "https://autos.yahoo.com.tw/new-cars/model/jaguar-xf-2020"
    },
    {
        "brand": "Jaguar",
        "model": "2019 Jaguar E-Pace",
        "price": "192 - 222",
        "url": "https://autos.yahoo.com.tw/new-cars/model/jaguar-e-pace-2019"
    },
    {
        "brand": "Jaguar",
        "model": "2019 Jaguar F-Pace",
        "price": "276 - 381",
        "url": "https://autos.yahoo.com.tw/new-cars/model/jaguar-f-pace-2019"
    },
    {
        "brand": "Jaguar",
        "model": "2019 Jaguar F-Type Coupe",
        "price": "328 - 760",
        "url": "https://autos.yahoo.com.tw/new-cars/model/jaguar-f-type-coupe-2019"
    },
    {
        "brand": "Jaguar",
        "model": "2019 Jaguar XE",
        "price": "198 - 270",
        "url": "https://autos.yahoo.com.tw/new-cars/model/jaguar-xe-2019"
    },
    {
        "brand": "Jaguar",
        "model": "2019 Jaguar XF",
        "price": "240 - 357",
        "url": "https://autos.yahoo.com.tw/new-cars/model/jaguar-xf-2019"
    },
    {
        "brand": "Jaguar",
        "model": "2019 Jaguar XJ",
        "price": "542 - 562",
        "url": "https://autos.yahoo.com.tw/new-cars/model/jaguar-xj-2019"
    },
    {
        "brand": "Jaguar",
        "model": "2018 Jaguar E-Pace",
        "price": "179 - 237",
        "url": "https://autos.yahoo.com.tw/new-cars/model/jaguar-e-pace-2018"
    },
    {
        "brand": "Jaguar",
        "model": "2018 Jaguar F-Pace",
        "price": "256 - 370",
        "url": "https://autos.yahoo.com.tw/new-cars/model/jaguar-f-pace-2018"
    },
    {
        "brand": "Jaguar",
        "model": "2018 Jaguar F-Type Coupe",
        "price": "328 - 760",
        "url": "https://autos.yahoo.com.tw/new-cars/model/jaguar-f-type-coupe-2018"
    },
    {
        "brand": "Jaguar",
        "model": "2018 Jaguar XE",
        "price": "198 - 270",
        "url": "https://autos.yahoo.com.tw/new-cars/model/jaguar-xe-2018"
    },
    {
        "brand": "Jaguar",
        "model": "2018 Jaguar XF",
        "price": "233 - 342",
        "url": "https://autos.yahoo.com.tw/new-cars/model/jaguar-xf-2018"
    },
    {
        "brand": "Jaguar",
        "model": "2018 Jaguar XJ",
        "price": "542 - 562",
        "url": "https://autos.yahoo.com.tw/new-cars/model/jaguar-xj-2018"
    },
    {
        "brand": "Jaguar",
        "model": "2017 Jaguar F-Pace",
        "price": "299 - 439",
        "url": "https://autos.yahoo.com.tw/new-cars/model/jaguar-f-pace-2017"
    },
    {
        "brand": "Jaguar",
        "model": "2017 Jaguar F-Type",
        "price": "560 - 820",
        "url": "https://autos.yahoo.com.tw/new-cars/model/jaguar-f-type-2017"
    },
    {
        "brand": "Jaguar",
        "model": "2017 Jaguar F-Type Coupe",
        "price": "379 - 860",
        "url": "https://autos.yahoo.com.tw/new-cars/model/jaguar-f-type-coupe-2017"
    },
    {
        "brand": "Jaguar",
        "model": "2017 Jaguar XE",
        "price": "192 - 299",
        "url": "https://autos.yahoo.com.tw/new-cars/model/jaguar-xe-2017"
    },
    {
        "brand": "Jaguar",
        "model": "2017 Jaguar XF",
        "price": "241 - 450",
        "url": "https://autos.yahoo.com.tw/new-cars/model/jaguar-xf-2017"
    },
    {
        "brand": "Jaguar",
        "model": "2017 Jaguar XJ",
        "price": "325 - 529",
        "url": "https://autos.yahoo.com.tw/new-cars/model/jaguar-xj-2017"
    },
    {
        "brand": "Jaguar",
        "model": "2016 Jaguar F-Type",
        "price": "590 - 905",
        "url": "https://autos.yahoo.com.tw/new-cars/model/jaguar-f-type-2016"
    },
    {
        "brand": "Jaguar",
        "model": "2016 Jaguar F-Type Coupe",
        "price": "435 - 825",
        "url": "https://autos.yahoo.com.tw/new-cars/model/jaguar-f-type-coupe-2016"
    },
    {
        "brand": "Jaguar",
        "model": "2016 Jaguar XE",
        "price": "206 - 319",
        "url": "https://autos.yahoo.com.tw/new-cars/model/jaguar-xe-2016"
    },
    {
        "brand": "Jaguar",
        "model": "2016 Jaguar XF",
        "price": "261 - 481",
        "url": "https://autos.yahoo.com.tw/new-cars/model/jaguar-xf-2016"
    },
    {
        "brand": "Jaguar",
        "model": "2016 Jaguar XF Sportbrake",
        "price": "269 - 269",
        "url": "https://autos.yahoo.com.tw/new-cars/model/jaguar-xf-sportbrake-2016"
    },
    {
        "brand": "Jaguar",
        "model": "2016 Jaguar XJ",
        "price": "385 - 575",
        "url": "https://autos.yahoo.com.tw/new-cars/model/jaguar-xj-2016"
    },
    {
        "brand": "Jaguar",
        "model": "2015 Jaguar F-Type",
        "price": "578 - 888",
        "url": "https://autos.yahoo.com.tw/new-cars/model/jaguar-f-type-2015"
    },
    {
        "brand": "Jaguar",
        "model": "2015 Jaguar F-Type Coupe",
        "price": "398 - 808",
        "url": "https://autos.yahoo.com.tw/new-cars/model/jaguar-f-type-coupe-2015"
    },
    {
        "brand": "Jaguar",
        "model": "2015 Jaguar XE",
        "price": "199 - 309",
        "url": "https://autos.yahoo.com.tw/new-cars/model/jaguar-xe-2015"
    },
    {
        "brand": "Jaguar",
        "model": "2015 Jaguar XF",
        "price": "242 - 635",
        "url": "https://autos.yahoo.com.tw/new-cars/model/jaguar-xf-2015"
    },
    {
        "brand": "Jaguar",
        "model": "2015 Jaguar XF Sportbrake",
        "price": "269 - 269",
        "url": "https://autos.yahoo.com.tw/new-cars/model/jaguar-xf-sportbrake-2015"
    },
    {
        "brand": "Jaguar",
        "model": "2015 Jaguar XJ",
        "price": "365 - 539",
        "url": "https://autos.yahoo.com.tw/new-cars/model/jaguar-xj-2015"
    },
    {
        "brand": "Jaguar",
        "model": "2014 Jaguar F-Type",
        "price": "568 - 728",
        "url": "https://autos.yahoo.com.tw/new-cars/model/jaguar-f-type-2014"
    },
    {
        "brand": "Jaguar",
        "model": "2014 Jaguar F-Type Coupe",
        "price": "395 - 768",
        "url": "https://autos.yahoo.com.tw/new-cars/model/jaguar-f-type-coupe-2014"
    },
    {
        "brand": "Jaguar",
        "model": "2014 Jaguar XF",
        "price": "242 - 635",
        "url": "https://autos.yahoo.com.tw/new-cars/model/jaguar-xf-2014"
    },
    {
        "brand": "Jaguar",
        "model": "2014 Jaguar XJ",
        "price": "365 - 539",
        "url": "https://autos.yahoo.com.tw/new-cars/model/jaguar-xj-2014"
    },
    {
        "brand": "Jaguar",
        "model": "2013 Jaguar XF",
        "price": "246 - 635",
        "url": "https://autos.yahoo.com.tw/new-cars/model/jaguar-xf-2013"
    },
    {
        "brand": "Jaguar",
        "model": "2013 Jaguar XJ",
        "price": "365 - 565",
        "url": "https://autos.yahoo.com.tw/new-cars/model/jaguar-xj-2013"
    },
    {
        "brand": "Jaguar",
        "model": "2012 Jaguar XF",
        "price": "238 - 618",
        "url": "https://autos.yahoo.com.tw/new-cars/model/jaguar-xf-2012"
    },
    {
        "brand": "Jaguar",
        "model": "2012 Jaguar XJ",
        "price": "398 - 898",
        "url": "https://autos.yahoo.com.tw/new-cars/model/jaguar-xj-2012"
    },
    {
        "brand": "Jaguar",
        "model": "2012 Jaguar XKR",
        "price": "768 - 928",
        "url": "https://autos.yahoo.com.tw/new-cars/model/jaguar-xkr-2012"
    },
    {
        "brand": "Jaguar",
        "model": "2011 Jaguar X-Type",
        "price": "226 - 226",
        "url": "https://autos.yahoo.com.tw/new-cars/model/jaguar-x-type-2011"
    },
    {
        "brand": "Jaguar",
        "model": "2011 Jaguar XF",
        "price": "299 - 559",
        "url": "https://autos.yahoo.com.tw/new-cars/model/jaguar-xf-2011"
    },
    {
        "brand": "Jaguar",
        "model": "2011 Jaguar XJ",
        "price": "470 - 806",
        "url": "https://autos.yahoo.com.tw/new-cars/model/jaguar-xj-2011"
    },
    {
        "brand": "Jaguar",
        "model": "2011 Jaguar XKR",
        "price": "689 - 759",
        "url": "https://autos.yahoo.com.tw/new-cars/model/jaguar-xkr-2011"
    },
    {
        "brand": "Jaguar",
        "model": "2010 Jaguar X-Type",
        "price": "226 - 226",
        "url": "https://autos.yahoo.com.tw/new-cars/model/jaguar-x-type-2010"
    },
    {
        "brand": "Jaguar",
        "model": "2010 Jaguar XF",
        "price": "299 - 529",
        "url": "https://autos.yahoo.com.tw/new-cars/model/jaguar-xf-2010"
    },
    {
        "brand": "Jaguar",
        "model": "2010 Jaguar XJ",
        "price": "470 - 806",
        "url": "https://autos.yahoo.com.tw/new-cars/model/jaguar-xj-2010"
    },
    {
        "brand": "Jaguar",
        "model": "2010 Jaguar XKR",
        "price": "679 - 739",
        "url": "https://autos.yahoo.com.tw/new-cars/model/jaguar-xkr-2010"
    },
    {
        "brand": "Jaguar",
        "model": "2009 Jaguar Sovereign",
        "price": "469 - 469",
        "url": "https://autos.yahoo.com.tw/new-cars/model/jaguar-sovereign-2009"
    },
    {
        "brand": "Jaguar",
        "model": "2009 Jaguar X-Type",
        "price": "226 - 226",
        "url": "https://autos.yahoo.com.tw/new-cars/model/jaguar-x-type-2009"
    },
    {
        "brand": "Jaguar",
        "model": "2009 Jaguar XF",
        "price": "299 - 519",
        "url": "https://autos.yahoo.com.tw/new-cars/model/jaguar-xf-2009"
    },
    {
        "brand": "Jaguar",
        "model": "2009 Jaguar XK",
        "price": "585 - 649",
        "url": "https://autos.yahoo.com.tw/new-cars/model/jaguar-xk-2009"
    },
    {
        "brand": "Jaguar",
        "model": "2008 Jaguar Daimler",
        "price": "559 - 559",
        "url": "https://autos.yahoo.com.tw/new-cars/model/jaguar-daimler-2008"
    },
    {
        "brand": "Jaguar",
        "model": "2008 Jaguar Sovereign",
        "price": "429 - 429",
        "url": "https://autos.yahoo.com.tw/new-cars/model/jaguar-sovereign-2008"
    },
    {
        "brand": "Jaguar",
        "model": "2008 Jaguar X-Type",
        "price": "179 - 226",
        "url": "https://autos.yahoo.com.tw/new-cars/model/jaguar-x-type-2008"
    },
    {
        "brand": "Jaguar",
        "model": "2008 Jaguar XF",
        "price": "309 - 449",
        "url": "https://autos.yahoo.com.tw/new-cars/model/jaguar-xf-2008"
    },
    {
        "brand": "Jaguar",
        "model": "2008 Jaguar XJ6",
        "price": "326 - 363",
        "url": "https://autos.yahoo.com.tw/new-cars/model/jaguar-xj6-2008"
    },
    {
        "brand": "Jaguar",
        "model": "2008 Jaguar XK",
        "price": "497 - 585",
        "url": "https://autos.yahoo.com.tw/new-cars/model/jaguar-xk-2008"
    },
    {
        "brand": "Jaguar",
        "model": "2007 Jaguar XKR",
        "price": "559 - 559",
        "url": "https://autos.yahoo.com.tw/new-cars/model/jaguar-xkr-2007"
    }
]